{"AAA": {"GGT": 0, "AAT": 50, "ATC": 0, "CCC": 0, "GCC": 0, "TTG": 0, "GAA": 53, "GAC": 1, "GCA": 1, "AGC": 2, "AAG": 245, "CCA": 0, "TGC": 0, "CCG": 0, "TCA": 1, "GTC": 0, "GGC": 0, "CTA": 3, "TCT": 0, "CAA": 27, "CGC": 0, "ACC": 4, "TTC": 0, "GAG": 11, "ATA": 10, "TGT": 0, "CTC": 0, "CGT": 0, "GCT": 0, "GAT": 3, "TAC": 0, "GCG": 0, "GGA": 2, "TCG": 0, "GTA": 2, "CTG": 0, "GTT": 2, "AGG": 2, "AAC": 15, "ATG": 1, "CGG": 0, "CGA": 2, "TGG": 0, "ACG": 0, "TTA": 1, "CCT": 0, "CAC": 0, "TCC": 0, "TAT": 1, "ACT": 2, "TGA": 1, "ACA": 11, "CAG": 2, "TAG": 0, "ATT": 1, "AGA": 53, "CAT": 1, "TTT": 0, "TAA": 4, "GGG": 0, "GTG": 0, "CTT": 0, "AGT": 4}, "AAC": {"GGT": 0, "AAT": 312, "ATC": 0, "CCC": 0, "GCC": 0, "TTG": 0, "GAA": 1, "GAC": 38, "GCA": 0, "AGC": 45, "AAG": 3, "CCA": 0, "TGC": 1, "CCG": 0, "TCA": 1, "GTC": 1, "GGC": 2, "CTA": 0, "TCT": 0, "CAA": 1, "CGC": 1, "ACC": 7, "TTC": 1, "GAG": 2, "AAA": 36, "ATA": 1, "TGT": 0, "CTC": 1, "CGT": 0, "GCT": 0, "GAT": 7, "TAC": 7, "GCG": 0, "GGA": 0, "TCG": 0, "GTA": 0, "CTG": 0, "GTT": 0, "AGG": 0, "ATG": 0, "CGG": 0, "CGA": 0, "TGG": 0, "ACG": 0, "TTA": 0, "CCT": 0, "CAC": 1, "TCC": 0, "TAT": 1, "ACT": 1, "TGA": 0, "ACA": 2, "CAG": 1, "TAG": 0, "ATT": 0, "AGA": 0, "CAT": 0, "TTT": 0, "TAA": 0, "GGG": 0, "GTG": 0, "CTT": 0, "AGT": 4}, "AAG": {"GGT": 0, "AAT": 15, "ATC": 0, "CCC": 1, "GCC": 0, "TTG": 0, "GAA": 2, "GAC": 1, "GCA": 0, "AGC": 0, "CCA": 0, "TGC": 0, "CCG": 0, "TCA": 0, "GTC": 0, "GGC": 0, "CTA": 0, "TCT": 1, "CAA": 1, "CGC": 0, "ACC": 0, "TTC": 1, "GAG": 25, "AAA": 266, "ATA": 2, "TGT": 0, "CTC": 0, "CGT": 0, "GCT": 1, "GAT": 1, "TAC": 0, "GCG": 0, "GGA": 0, "TCG": 0, "GTA": 0, "CTG": 0, "GTT": 0, "AGG": 15, "AAC": 7, "ATG": 8, "CGG": 0, "CGA": 0, "TGG": 0, "ACG": 2, "TTA": 0, "CCT": 0, "CAC": 0, "TCC": 0, "TAT": 0, "ACT": 0, "TGA": 0, "ACA": 0, "CAG": 3, "TAG": 0, "ATT": 0, "AGA": 3, "CAT": 1, "TTT": 0, "TAA": 0, "GGG": 0, "GTG": 2, "CTT": 0, "AGT": 0}, "AAT": {"GGT": 9, "ATC": 0, "CCC": 0, "GCC": 1, "TTG": 0, "GAA": 13, "GAC": 5, "GCA": 3, "AGC": 7, "AAG": 19, "CCA": 0, "TGC": 0, "CCG": 0, "TCA": 0, "GTC": 0, "GGC": 0, "CTA": 0, "TCT": 3, "CAA": 0, "CGC": 0, "ACC": 0, "TTC": 0, "GAG": 4, "AAA": 55, "ATA": 0, "TGT": 1, "CTC": 0, "CGT": 0, "GCT": 2, "GAT": 87, "TAC": 1, "GCG": 0, "GGA": 1, "TCG": 1, "GTA": 0, "CTG": 0, "GTT": 1, "AGG": 1, "AAC": 252, "ATG": 0, "CGG": 0, "CGA": 0, "TGG": 0, "ACG": 0, "TTA": 0, "CCT": 0, "CAC": 2, "TCC": 0, "TAT": 10, "ACT": 14, "TGA": 0, "ACA": 6, "CAG": 0, "TAG": 0, "ATT": 11, "AGA": 2, "CAT": 11, "TTT": 0, "TAA": 0, "GGG": 0, "GTG": 0, "CTT": 2, "AGT": 48}, "ACA": {"GGT": 0, "AAT": 8, "ATC": 1, "CCC": 1, "GCC": 5, "TTG": 0, "GAA": 1, "GAC": 0, "GCA": 74, "AGC": 3, "AAG": 3, "CCA": 1, "TGC": 0, "CCG": 0, "TCA": 46, "GTC": 0, "GGC": 1, "CTA": 0, "TCT": 4, "CAA": 3, "CGC": 0, "ACC": 93, "TTC": 0, "GAG": 3, "AAA": 16, "ATA": 49, "TGT": 0, "CTC": 0, "CGT": 0, "GCT": 2, "GAT": 4, "TAC": 0, "GCG": 1, "GGA": 1, "TCG": 1, "GTA": 2, "CTG": 0, "GTT": 0, "AGG": 1, "AAC": 1, "ATG": 0, "CGG": 0, "CGA": 0, "TGG": 0, "ACG": 77, "TTA": 1, "CCT": 0, "CAC": 0, "TCC": 1, "TAT": 1, "ACT": 167, "TGA": 0, "CAG": 0, "TAG": 0, "ATT": 1, "AGA": 6, "CAT": 0, "TTT": 0, "TAA": 1, "GGG": 0, "GTG": 0, "CTT": 0, "AGT": 2}, "ACC": {"GGT": 0, "AAT": 1, "ATC": 14, "CCC": 2, "GCC": 26, "TTG": 1, "GAA": 0, "GAC": 3, "GCA": 5, "AGC": 9, "AAG": 0, "CCA": 0, "TGC": 0, "CCG": 0, "TCA": 0, "GTC": 1, "GGC": 0, "CTA": 0, "TCT": 2, "CAA": 0, "CGC": 1, "TTC": 0, "GAG": 0, "AAA": 2, "ATA": 0, "TGT": 0, "CTC": 1, "CGT": 0, "GCT": 1, "GAT": 1, "TAC": 0, "GCG": 1, "GGA": 0, "TCG": 0, "GTA": 0, "CTG": 0, "GTT": 0, "AGG": 0, "AAC": 14, "ATG": 1, "CGG": 0, "CGA": 0, "TGG": 0, "ACG": 6, "TTA": 0, "CCT": 1, "CAC": 1, "TCC": 12, "TAT": 0, "ACT": 152, "TGA": 0, "ACA": 92, "CAG": 0, "TAG": 0, "ATT": 1, "AGA": 0, "CAT": 0, "TTT": 1, "TAA": 0, "GGG": 0, "GTG": 0, "CTT": 0, "AGT": 0}, "ACG": {"GGT": 0, "AAT": 0, "ATC": 0, "CCC": 0, "GCC": 0, "TTG": 0, "GAA": 0, "GAC": 0, "GCA": 4, "AGC": 0, "AAG": 4, "CCA": 0, "TGC": 0, "CCG": 1, "TCA": 3, "GTC": 0, "GGC": 0, "CTA": 0, "TCT": 1, "CAA": 0, "CGC": 0, "ACC": 9, "TTC": 0, "GAG": 0, "AAA": 0, "ATA": 0, "TGT": 0, "CTC": 0, "CGT": 0, "GCT": 0, "GAT": 0, "TAC": 0, "GCG": 3, "GGA": 0, "TCG": 2, "GTA": 1, "CTG": 0, "GTT": 0, "AGG": 1, "AAC": 0, "ATG": 9, "CGG": 0, "CGA": 0, "TGG": 0, "TTA": 0, "CCT": 0, "CAC": 0, "TCC": 0, "TAT": 0, "ACT": 25, "TGA": 0, "ACA": 70, "CAG": 0, "TAG": 0, "ATT": 0, "AGA": 0, "CAT": 0, "TTT": 0, "TAA": 0, "GGG": 0, "GTG": 0, "CTT": 0, "AGT": 0}, "ACT": {"GGT": 1, "AAT": 12, "ATC": 3, "CCC": 0, "GCC": 0, "TTG": 1, "GAA": 0, "GAC": 0, "GCA": 2, "AGC": 1, "AAG": 3, "CCA": 0, "TGC": 0, "CCG": 0, "TCA": 4, "GTC": 0, "GGC": 0, "CTA": 0, "TCT": 24, "CAA": 1, "CGC": 0, "ACC": 143, "TTC": 0, "GAG": 0, "AAA": 1, "ATA": 3, "TGT": 0, "CTC": 0, "CGT": 0, "GCT": 57, "GAT": 2, "TAC": 0, "GCG": 0, "GGA": 0, "TCG": 3, "GTA": 1, "CTG": 0, "GTT": 4, "AGG": 0, "AAC": 3, "ATG": 0, "CGG": 0, "CGA": 0, "TGG": 0, "ACG": 24, "TTA": 0, "CCT": 7, "CAC": 0, "TCC": 1, "TAT": 1, "TGA": 0, "ACA": 145, "CAG": 0, "TAG": 0, "ATT": 17, "AGA": 0, "CAT": 0, "TTT": 1, "TAA": 0, "GGG": 0, "GTG": 0, "CTT": 0, "AGT": 12}, "AGA": {"GGT": 2, "AAT": 1, "ATC": 0, "CCC": 0, "GCC": 0, "TTG": 0, "GAA": 2, "GAC": 0, "GCA": 0, "AGC": 5, "AAG": 1, "CCA": 0, "TGC": 0, "CCG": 0, "TCA": 0, "GTC": 0, "GGC": 0, "CTA": 0, "TCT": 0, "CAA": 1, "CGC": 4, "ACC": 1, "TTC": 0, "GAG": 0, "AAA": 68, "ATA": 12, "TGT": 0, "CTC": 0, "CGT": 4, "GCT": 1, "GAT": 0, "TAC": 0, "GCG": 0, "GGA": 7, "TCG": 0, "GTA": 0, "CTG": 0, "GTT": 0, "AGG": 60, "AAC": 1, "ATG": 1, "CGG": 0, "CGA": 33, "TGG": 0, "ACG": 1, "TTA": 0, "CCT": 0, "CAC": 0, "TCC": 0, "TAT": 1, "ACT": 0, "TGA": 1, "ACA": 5, "CAG": 0, "TAG": 0, "ATT": 1, "CAT": 0, "TTT": 0, "TAA": 0, "GGG": 0, "GTG": 1, "CTT": 0, "AGT": 8}, "AGC": {"GGT": 2, "AAT": 6, "ATC": 5, "CCC": 0, "GCC": 1, "TTG": 0, "GAA": 1, "GAC": 2, "GCA": 0, "AAG": 0, "CCA": 0, "TGC": 11, "CCG": 0, "TCA": 0, "GTC": 1, "GGC": 13, "CTA": 0, "TCT": 0, "CAA": 0, "CGC": 4, "ACC": 9, "TTC": 1, "GAG": 0, "AAA": 0, "ATA": 0, "TGT": 0, "CTC": 0, "CGT": 0, "GCT": 1, "GAT": 2, "TAC": 2, "GCG": 0, "GGA": 1, "TCG": 0, "GTA": 0, "CTG": 0, "GTT": 0, "AGG": 1, "AAC": 34, "ATG": 0, "CGG": 0, "CGA": 0, "TGG": 0, "ACG": 0, "TTA": 0, "CCT": 0, "CAC": 1, "TCC": 0, "TAT": 0, "ACT": 1, "TGA": 0, "ACA": 1, "CAG": 0, "TAG": 0, "ATT": 3, "AGA": 6, "CAT": 0, "TTT": 0, "TAA": 0, "GGG": 0, "GTG": 0, "CTT": 0, "AGT": 164}, "AGG": {"GGT": 0, "AAT": 1, "ATC": 1, "CCC": 0, "GCC": 0, "TTG": 0, "GAA": 0, "GAC": 0, "GCA": 0, "AGC": 0, "AAG": 19, "CCA": 0, "TGC": 0, "CCG": 0, "TCA": 1, "GTC": 0, "GGC": 0, "CTA": 0, "TCT": 0, "CAA": 0, "CGC": 1, "ACC": 0, "TTC": 0, "GAG": 1, "AAA": 2, "ATA": 0, "TGT": 0, "CTC": 0, "CGT": 4, "GCT": 0, "GAT": 0, "TAC": 0, "GCG": 0, "GGA": 0, "TCG": 0, "GTA": 0, "CTG": 0, "GTT": 0, "AAC": 0, "ATG": 0, "CGG": 2, "CGA": 1, "TGG": 1, "ACG": 1, "TTA": 0, "CCT": 0, "CAC": 0, "TCC": 0, "TAT": 1, "ACT": 0, "TGA": 0, "ACA": 0, "CAG": 1, "TAG": 6, "ATT": 0, "AGA": 69, "CAT": 0, "TTT": 0, "TAA": 0, "GGG": 5, "GTG": 0, "CTT": 0, "AGT": 4}, "AGT": {"GGT": 17, "AAT": 38, "ATC": 0, "CCC": 0, "GCC": 1, "TTG": 0, "GAA": 1, "GAC": 0, "GCA": 1, "AGC": 131, "AAG": 0, "CCA": 0, "TGC": 1, "CCG": 0, "TCA": 1, "GTC": 0, "GGC": 0, "CTA": 0, "TCT": 2, "CAA": 0, "CGC": 1, "ACC": 1, "TTC": 0, "GAG": 1, "AAA": 1, "ATA": 0, "TGT": 6, "CTC": 0, "CGT": 3, "GCT": 1, "GAT": 4, "TAC": 0, "GCG": 0, "GGA": 2, "TCG": 2, "GTA": 1, "CTG": 0, "GTT": 1, "AGG": 4, "AAC": 3, "ATG": 1, "CGG": 0, "CGA": 0, "TGG": 0, "ACG": 0, "TTA": 0, "CCT": 0, "CAC": 0, "TCC": 0, "TAT": 2, "ACT": 20, "TGA": 0, "ACA": 5, "CAG": 0, "TAG": 0, "ATT": 3, "AGA": 8, "CAT": 0, "TTT": 1, "TAA": 0, "GGG": 0, "GTG": 0, "CTT": 0}, "ATA": {"GGT": 0, "AAT": 0, "ATC": 90, "CCC": 0, "GCC": 0, "TTG": 3, "GAA": 0, "GAC": 0, "GCA": 4, "AGC": 0, "AAG": 0, "CCA": 0, "TGC": 0, "CCG": 0, "TCA": 0, "GTC": 1, "GGC": 0, "CTA": 9, "TCT": 0, "CAA": 1, "CGC": 0, "ACC": 1, "TTC": 1, "GAG": 0, "AAA": 6, "TGT": 0, "CTC": 0, "CGT": 0, "GCT": 1, "GAT": 0, "TAC": 0, "GCG": 0, "GGA": 2, "TCG": 0, "GTA": 84, "CTG": 1, "GTT": 15, "AGG": 0, "AAC": 0, "ATG": 33, "CGG": 0, "CGA": 0, "TGG": 0, "ACG": 1, "TTA": 45, "CCT": 1, "CAC": 0, "TCC": 0, "TAT": 0, "ACT": 2, "TGA": 0, "ACA": 43, "CAG": 0, "TAG": 0, "ATT": 142, "AGA": 8, "CAT": 0, "TTT": 2, "TAA": 0, "GGG": 0, "GTG": 4, "CTT": 3, "AGT": 0}, "ATC": {"GGT": 0, "AAT": 0, "CCC": 0, "GCC": 0, "TTG": 0, "GAA": 0, "GAC": 1, "GCA": 0, "AGC": 1, "AAG": 0, "CCA": 0, "TGC": 0, "CCG": 0, "TCA": 0, "GTC": 17, "GGC": 1, "CTA": 0, "TCT": 0, "CAA": 0, "CGC": 0, "ACC": 12, "TTC": 6, "GAG": 0, "AAA": 0, "ATA": 95, "TGT": 0, "CTC": 7, "CGT": 0, "GCT": 0, "GAT": 0, "TAC": 0, "GCG": 1, "GGA": 0, "TCG": 0, "GTA": 0, "CTG": 0, "GTT": 3, "AGG": 1, "AAC": 3, "ATG": 4, "CGG": 0, "CGA": 0, "TGG": 0, "ACG": 0, "TTA": 0, "CCT": 0, "CAC": 0, "TCC": 0, "TAT": 0, "ACT": 3, "TGA": 0, "ACA": 0, "CAG": 0, "TAG": 0, "ATT": 171, "AGA": 0, "CAT": 0, "TTT": 0, "TAA": 0, "GGG": 0, "GTG": 0, "CTT": 0, "AGT": 0}, "ATG": {"GGT": 0, "AAT": 0, "ATC": 4, "CCC": 0, "GCC": 0, "TTG": 10, "GAA": 0, "GAC": 0, "GCA": 2, "AGC": 0, "AAG": 12, "CCA": 0, "TGC": 0, "CCG": 0, "TCA": 0, "GTC": 0, "GGC": 0, "CTA": 1, "TCT": 0, "CAA": 0, "CGC": 0, "ACC": 0, "TTC": 0, "GAG": 0, "AAA": 2, "ATA": 58, "TGT": 0, "CTC": 0, "CGT": 0, "GCT": 0, "GAT": 0, "TAC": 0, "GCG": 0, "GGA": 0, "TCG": 0, "GTA": 5, "CTG": 12, "GTT": 0, "AGG": 3, "AAC": 0, "CGG": 0, "CGA": 0, "TGG": 0, "ACG": 8, "TTA": 3, "CCT": 0, "CAC": 0, "TCC": 0, "TAT": 0, "ACT": 0, "TGA": 0, "ACA": 1, "CAG": 0, "TAG": 0, "ATT": 13, "AGA": 0, "CAT": 0, "TTT": 0, "TAA": 0, "GGG": 0, "GTG": 12, "CTT": 1, "AGT": 0}, "ATT": {"GGT": 0, "AAT": 6, "ATC": 149, "CCC": 0, "GCC": 0, "TTG": 0, "GAA": 0, "GAC": 0, "GCA": 1, "AGC": 1, "AAG": 0, "CCA": 0, "TGC": 0, "CCG": 0, "TCA": 1, "GTC": 2, "GGC": 0, "CTA": 0, "TCT": 0, "CAA": 1, "CGC": 0, "ACC": 2, "TTC": 1, "GAG": 0, "AAA": 2, "ATA": 139, "TGT": 0, "CTC": 0, "CGT": 0, "GCT": 1, "GAT": 1, "TAC": 0, "GCG": 0, "GGA": 0, "TCG": 0, "GTA": 5, "CTG": 1, "GTT": 82, "AGG": 0, "AAC": 0, "ATG": 8, "CGG": 0, "CGA": 0, "TGG": 1, "ACG": 1, "TTA": 2, "CCT": 0, "CAC": 0, "TCC": 0, "TAT": 2, "ACT": 15, "TGA": 0, "ACA": 1, "CAG": 0, "TAG": 0, "AGA": 0, "CAT": 1, "TTT": 24, "TAA": 0, "GGG": 0, "GTG": 3, "CTT": 15, "AGT": 1}, "CAA": {"GGT": 0, "AAT": 0, "ATC": 0, "CCC": 0, "GCC": 0, "TTG": 0, "GAA": 15, "GAC": 0, "GCA": 0, "AGC": 0, "AAG": 3, "CCA": 8, "TGC": 0, "CCG": 0, "TCA": 0, "GTC": 0, "GGC": 0, "CTA": 4, "TCT": 0, "CGC": 0, "ACC": 0, "TTC": 0, "GAG": 2, "AAA": 35, "ATA": 0, "TGT": 0, "CTC": 0, "CGT": 1, "GCT": 0, "GAT": 0, "TAC": 0, "GCG": 0, "GGA": 0, "TCG": 0, "GTA": 2, "CTG": 0, "GTT": 0, "AGG": 0, "AAC": 1, "ATG": 0, "CGG": 2, "CGA": 13, "TGG": 0, "ACG": 0, "TTA": 0, "CCT": 0, "CAC": 3, "TCC": 0, "TAT": 0, "ACT": 1, "TGA": 0, "ACA": 3, "CAG": 95, "TAG": 0, "ATT": 1, "AGA": 2, "CAT": 10, "TTT": 0, "TAA": 2, "GGG": 0, "GTG": 0, "CTT": 1, "AGT": 0}, "CAC": {"GGT": 0, "AAT": 1, "ATC": 1, "CCC": 1, "GCC": 0, "TTG": 0, "GAA": 0, "GAC": 0, "GCA": 0, "AGC": 0, "AAG": 0, "CCA": 1, "TGC": 0, "CCG": 0, "TCA": 0, "GTC": 1, "GGC": 0, "CTA": 0, "TCT": 0, "CAA": 0, "CGC": 2, "ACC": 0, "TTC": 0, "GAG": 0, "AAA": 0, "ATA": 0, "TGT": 0, "CTC": 3, "CGT": 1, "GCT": 0, "GAT": 0, "TAC": 2, "GCG": 0, "GGA": 0, "TCG": 0, "GTA": 0, "CTG": 0, "GTT": 0, "AGG": 0, "AAC": 5, "ATG": 0, "CGG": 0, "CGA": 0, "TGG": 0, "ACG": 0, "TTA": 0, "CCT": 0, "TCC": 0, "TAT": 1, "ACT": 0, "TGA": 0, "ACA": 0, "CAG": 1, "TAG": 0, "ATT": 0, "AGA": 0, "CAT": 66, "TTT": 0, "TAA": 0, "GGG": 0, "GTG": 0, "CTT": 0, "AGT": 0}, "CAG": {"GGT": 0, "AAT": 2, "ATC": 0, "CCC": 1, "GCC": 0, "TTG": 1, "GAA": 0, "GAC": 0, "GCA": 0, "AGC": 0, "AAG": 7, "CCA": 0, "TGC": 0, "CCG": 0, "TCA": 0, "GTC": 0, "GGC": 0, "CTA": 0, "TCT": 0, "CAA": 101, "CGC": 0, "ACC": 0, "TTC": 0, "GAG": 3, "AAA": 2, "ATA": 0, "TGT": 0, "CTC": 0, "CGT": 0, "GCT": 0, "GAT": 1, "TAC": 0, "GCG": 0, "GGA": 0, "TCG": 0, "GTA": 0, "CTG": 1, "GTT": 0, "AGG": 0, "AAC": 0, "ATG": 0, "CGG": 4, "CGA": 0, "TGG": 0, "ACG": 0, "TTA": 0, "CCT": 1, "CAC": 2, "TCC": 0, "TAT": 0, "ACT": 0, "TGA": 0, "ACA": 0, "TAG": 0, "ATT": 0, "AGA": 0, "CAT": 1, "TTT": 0, "TAA": 0, "GGG": 0, "GTG": 0, "CTT": 0, "AGT": 0}, "CAT": {"GGT": 1, "AAT": 2, "ATC": 0, "CCC": 0, "GCC": 0, "TTG": 0, "GAA": 1, "GAC": 0, "GCA": 0, "AGC": 0, "AAG": 0, "CCA": 0, "TGC": 0, "CCG": 0, "TCA": 0, "GTC": 0, "GGC": 0, "CTA": 0, "TCT": 1, "CAA": 4, "CGC": 1, "ACC": 0, "TTC": 0, "GAG": 0, "AAA": 2, "ATA": 0, "TGT": 0, "CTC": 0, "CGT": 4, "GCT": 0, "GAT": 4, "TAC": 0, "GCG": 0, "GGA": 0, "TCG": 0, "GTA": 0, "CTG": 0, "GTT": 0, "AGG": 0, "AAC": 1, "ATG": 0, "CGG": 0, "CGA": 0, "TGG": 0, "ACG": 0, "TTA": 0, "CCT": 0, "CAC": 59, "TCC": 0, "TAT": 13, "ACT": 1, "TGA": 0, "ACA": 0, "CAG": 3, "TAG": 0, "ATT": 0, "AGA": 0, "TTT": 0, "TAA": 0, "GGG": 0, "GTG": 0, "CTT": 4, "AGT": 0}, "CCA": {"GGT": 0, "AAT": 0, "ATC": 0, "CCC": 64, "GCC": 0, "TTG": 0, "GAA": 0, "GAC": 0, "GCA": 5, "AGC": 0, "AAG": 0, "TGC": 0, "CCG": 74, "TCA": 15, "GTC": 0, "GGC": 0, "CTA": 0, "TCT": 1, "CAA": 6, "CGC": 0, "ACC": 0, "TTC": 0, "GAG": 0, "AAA": 3, "ATA": 1, "TGT": 0, "CTC": 1, "CGT": 0, "GCT": 0, "GAT": 0, "TAC": 0, "GCG": 0, "GGA": 0, "TCG": 0, "GTA": 1, "CTG": 0, "GTT": 0, "AGG": 0, "AAC": 0, "ATG": 0, "CGG": 0, "CGA": 1, "TGG": 0, "ACG": 0, "TTA": 0, "CCT": 93, "CAC": 1, "TCC": 1, "TAT": 0, "ACT": 2, "TGA": 0, "ACA": 11, "CAG": 1, "TAG": 0, "ATT": 0, "AGA": 0, "CAT": 0, "TTT": 0, "TAA": 0, "GGG": 0, "GTG": 0, "CTT": 0, "AGT": 1}, "CCC": {"GGT": 0, "AAT": 0, "ATC": 0, "GCC": 1, "TTG": 0, "GAA": 1, "GAC": 0, "GCA": 1, "AGC": 1, "AAG": 0, "CCA": 69, "TGC": 0, "CCG": 9, "TCA": 1, "GTC": 0, "GGC": 0, "CTA": 0, "TCT": 0, "CAA": 0, "CGC": 0, "ACC": 7, "TTC": 0, "GAG": 0, "AAA": 0, "ATA": 0, "TGT": 0, "CTC": 3, "CGT": 0, "GCT": 0, "GAT": 0, "TAC": 0, "GCG": 0, "GGA": 0, "TCG": 1, "GTA": 0, "CTG": 0, "GTT": 0, "AGG": 0, "AAC": 0, "ATG": 0, "CGG": 0, "CGA": 0, "TGG": 0, "ACG": 0, "TTA": 0, "CCT": 144, "CAC": 2, "TCC": 8, "TAT": 1, "ACT": 0, "TGA": 0, "ACA": 1, "CAG": 0, "TAG": 0, "ATT": 0, "AGA": 0, "CAT": 0, "TTT": 0, "TAA": 0, "GGG": 0, "GTG": 0, "CTT": 0, "AGT": 0}, "CCG": {"GGT": 0, "AAT": 0, "ATC": 0, "CCC": 13, "GCC": 0, "TTG": 0, "GAA": 0, "GAC": 0, "GCA": 0, "AGC": 0, "AAG": 0, "CCA": 59, "TGC": 0, "TCA": 0, "GTC": 0, "GGC": 0, "CTA": 0, "TCT": 0, "CAA": 0, "CGC": 0, "ACC": 0, "TTC": 0, "GAG": 0, "AAA": 0, "ATA": 0, "TGT": 0, "CTC": 0, "CGT": 0, "GCT": 0, "GAT": 0, "TAC": 0, "GCG": 3, "GGA": 0, "TCG": 9, "GTA": 0, "CTG": 3, "GTT": 0, "AGG": 0, "AAC": 0, "ATG": 0, "CGG": 1, "CGA": 0, "TGG": 0, "ACG": 0, "TTA": 0, "CCT": 41, "CAC": 0, "TCC": 0, "TAT": 0, "ACT": 0, "TGA": 0, "ACA": 0, "CAG": 3, "TAG": 0, "ATT": 0, "AGA": 0, "CAT": 0, "TTT": 0, "TAA": 0, "GGG": 0, "GTG": 0, "CTT": 1, "AGT": 0}, "CCT": {"GGT": 4, "AAT": 0, "ATC": 0, "CCC": 125, "GCC": 0, "TTG": 0, "GAA": 0, "GAC": 0, "GCA": 1, "AGC": 0, "AAG": 0, "CCA": 91, "TGC": 0, "CCG": 35, "TCA": 0, "GTC": 1, "GGC": 0, "CTA": 0, "TCT": 32, "CAA": 0, "CGC": 0, "ACC": 0, "TTC": 0, "GAG": 0, "AAA": 1, "ATA": 0, "TGT": 0, "CTC": 0, "CGT": 0, "GCT": 2, "GAT": 1, "TAC": 0, "GCG": 0, "GGA": 0, "TCG": 0, "GTA": 0, "CTG": 0, "GTT": 0, "AGG": 0, "AAC": 0, "ATG": 0, "CGG": 1, "CGA": 0, "TGG": 0, "ACG": 1, "TTA": 0, "CAC": 0, "TCC": 0, "TAT": 0, "ACT": 7, "TGA": 0, "ACA": 0, "CAG": 0, "TAG": 0, "ATT": 0, "AGA": 0, "CAT": 5, "TTT": 0, "TAA": 0, "GGG": 0, "GTG": 0, "CTT": 7, "AGT": 0}, "CGA": {"GGT": 0, "AAT": 0, "ATC": 0, "CCC": 0, "GCC": 0, "TTG": 0, "GAA": 0, "GAC": 0, "GCA": 0, "AGC": 0, "AAG": 0, "CCA": 0, "TGC": 0, "CCG": 0, "TCA": 0, "GTC": 0, "GGC": 0, "CTA": 2, "TCT": 0, "CAA": 14, "CGC": 10, "ACC": 0, "TTC": 0, "GAG": 0, "AAA": 2, "ATA": 2, "TGT": 0, "CTC": 0, "CGT": 38, "GCT": 0, "GAT": 0, "TAC": 0, "GCG": 0, "GGA": 0, "TCG": 0, "GTA": 0, "CTG": 0, "GTT": 0, "AGG": 1, "AAC": 0, "ATG": 0, "CGG": 21, "TGG": 0, "ACG": 0, "TTA": 0, "CCT": 0, "CAC": 0, "TCC": 0, "TAT": 1, "ACT": 0, "TGA": 0, "ACA": 0, "CAG": 0, "TAG": 0, "ATT": 0, "AGA": 41, "CAT": 1, "TTT": 0, "TAA": 0, "GGG": 0, "GTG": 0, "CTT": 0, "AGT": 0}, "CGC": {"GGT": 0, "AAT": 0, "ATC": 1, "CCC": 0, "GCC": 1, "TTG": 0, "GAA": 0, "GAC": 0, "GCA": 0, "AGC": 2, "AAG": 0, "CCA": 0, "TGC": 2, "CCG": 0, "TCA": 0, "GTC": 0, "GGC": 0, "CTA": 0, "TCT": 0, "CAA": 0, "ACC": 0, "TTC": 0, "GAG": 0, "AAA": 1, "ATA": 0, "TGT": 2, "CTC": 3, "CGT": 127, "GCT": 0, "GAT": 0, "TAC": 2, "GCG": 0, "GGA": 0, "TCG": 0, "GTA": 0, "CTG": 0, "GTT": 0, "AGG": 0, "AAC": 0, "ATG": 0, "CGG": 1, "CGA": 20, "TGG": 0, "ACG": 0, "TTA": 0, "CCT": 0, "CAC": 8, "TCC": 0, "TAT": 0, "ACT": 0, "TGA": 0, "ACA": 0, "CAG": 0, "TAG": 0, "ATT": 0, "AGA": 4, "CAT": 0, "TTT": 0, "TAA": 0, "GGG": 0, "GTG": 0, "CTT": 1, "AGT": 0}, "CGG": {"GGT": 0, "AAT": 0, "ATC": 0, "CCC": 0, "GCC": 0, "TTG": 0, "GAA": 0, "GAC": 0, "GCA": 0, "AGC": 0, "AAG": 0, "CCA": 0, "TGC": 1, "CCG": 0, "TCA": 0, "GTC": 0, "GGC": 0, "CTA": 0, "TCT": 0, "CAA": 0, "CGC": 7, "ACC": 0, "TTC": 0, "GAG": 0, "AAA": 0, "ATA": 0, "TGT": 0, "CTC": 0, "CGT": 11, "GCT": 0, "GAT": 0, "TAC": 0, "GCG": 0, "GGA": 0, "TCG": 0, "GTA": 0, "CTG": 1, "GTT": 0, "AGG": 5, "AAC": 0, "ATG": 0, "CGA": 12, "TGG": 1, "ACG": 0, "TTA": 0, "CCT": 0, "CAC": 0, "TCC": 0, "TAT": 0, "ACT": 0, "TGA": 0, "ACA": 0, "CAG": 5, "TAG": 0, "ATT": 0, "AGA": 1, "CAT": 0, "TTT": 0, "TAA": 0, "GGG": 0, "GTG": 0, "CTT": 0, "AGT": 0}, "CGT": {"GGT": 0, "AAT": 1, "ATC": 0, "CCC": 0, "GCC": 0, "TTG": 0, "GAA": 0, "GAC": 0, "GCA": 0, "AGC": 0, "AAG": 0, "CCA": 0, "TGC": 1, "CCG": 0, "TCA": 0, "GTC": 0, "GGC": 0, "CTA": 0, "TCT": 0, "CAA": 0, "CGC": 129, "ACC": 0, "TTC": 0, "GAG": 0, "AAA": 0, "ATA": 0, "TGT": 7, "CTC": 0, "GCT": 0, "GAT": 0, "TAC": 0, "GCG": 0, "GGA": 0, "TCG": 0, "GTA": 0, "CTG": 0, "GTT": 0, "AGG": 1, "AAC": 0, "ATG": 0, "CGG": 10, "CGA": 40, "TGG": 0, "ACG": 0, "TTA": 0, "CCT": 2, "CAC": 0, "TCC": 0, "TAT": 0, "ACT": 0, "TGA": 0, "ACA": 0, "CAG": 0, "TAG": 0, "ATT": 0, "AGA": 5, "CAT": 4, "TTT": 0, "TAA": 0, "GGG": 0, "GTG": 0, "CTT": 3, "AGT": 5}, "CTA": {"GGT": 0, "AAT": 0, "ATC": 0, "CCC": 0, "GCC": 0, "TTG": 9, "GAA": 0, "GAC": 0, "GCA": 1, "AGC": 0, "AAG": 0, "CCA": 1, "TGC": 0, "CCG": 0, "TCA": 0, "GTC": 0, "GGC": 0, "TCT": 0, "CAA": 5, "CGC": 0, "ACC": 0, "TTC": 1, "GAG": 0, "AAA": 0, "ATA": 23, "TGT": 0, "CTC": 22, "CGT": 0, "GCT": 0, "GAT": 0, "TAC": 0, "GCG": 0, "GGA": 0, "TCG": 0, "GTA": 13, "CTG": 57, "GTT": 0, "AGG": 0, "AAC": 0, "ATG": 0, "CGG": 0, "CGA": 2, "TGG": 0, "ACG": 0, "TTA": 80, "CCT": 0, "CAC": 0, "TCC": 0, "TAT": 0, "ACT": 0, "TGA": 0, "ACA": 1, "CAG": 0, "TAG": 0, "ATT": 1, "AGA": 1, "CAT": 0, "TTT": 1, "TAA": 0, "GGG": 0, "GTG": 0, "CTT": 29, "AGT": 0}, "CTC": {"GGT": 0, "AAT": 0, "ATC": 4, "CCC": 4, "GCC": 0, "TTG": 1, "GAA": 0, "GAC": 0, "GCA": 0, "AGC": 0, "AAG": 0, "CCA": 0, "TGC": 0, "CCG": 1, "TCA": 0, "GTC": 6, "GGC": 0, "CTA": 31, "TCT": 0, "CAA": 0, "CGC": 0, "ACC": 0, "TTC": 7, "GAG": 0, "AAA": 1, "ATA": 0, "TGT": 0, "CGT": 0, "GCT": 0, "GAT": 0, "TAC": 2, "GCG": 0, "GGA": 0, "TCG": 0, "GTA": 0, "CTG": 2, "GTT": 0, "AGG": 0, "AAC": 0, "ATG": 0, "CGG": 0, "CGA": 0, "TGG": 0, "ACG": 0, "TTA": 5, "CCT": 0, "CAC": 4, "TCC": 0, "TAT": 0, "ACT": 0, "TGA": 0, "ACA": 0, "CAG": 0, "TAG": 0, "ATT": 1, "AGA": 0, "CAT": 0, "TTT": 0, "TAA": 0, "GGG": 0, "GTG": 0, "CTT": 74, "AGT": 0}, "CTG": {"GGT": 0, "AAT": 0, "ATC": 0, "CCC": 0, "GCC": 0, "TTG": 45, "GAA": 0, "GAC": 0, "GCA": 0, "AGC": 0, "AAG": 1, "CCA": 0, "TGC": 0, "CCG": 0, "TCA": 0, "GTC": 0, "GGC": 0, "CTA": 52, "TCT": 0, "CAA": 0, "CGC": 0, "ACC": 0, "TTC": 0, "GAG": 0, "AAA": 0, "ATA": 2, "TGT": 0, "CTC": 2, "CGT": 0, "GCT": 0, "GAT": 0, "TAC": 0, "GCG": 1, "GGA": 0, "TCG": 0, "GTA": 0, "GTT": 0, "AGG": 0, "AAC": 0, "ATG": 1, "CGG": 0, "CGA": 0, "TGG": 0, "ACG": 0, "TTA": 4, "CCT": 0, "CAC": 0, "TCC": 0, "TAT": 0, "ACT": 0, "TGA": 0, "ACA": 0, "CAG": 0, "TAG": 0, "ATT": 1, "AGA": 0, "CAT": 0, "TTT": 0, "TAA": 0, "GGG": 0, "GTG": 2, "CTT": 19, "AGT": 0}, "CTT": {"GGT": 0, "AAT": 0, "ATC": 0, "CCC": 0, "GCC": 0, "TTG": 9, "GAA": 0, "GAC": 0, "GCA": 0, "AGC": 0, "AAG": 0, "CCA": 0, "TGC": 0, "CCG": 0, "TCA": 0, "GTC": 0, "GGC": 0, "CTA": 41, "TCT": 0, "CAA": 0, "CGC": 0, "ACC": 0, "TTC": 0, "GAG": 1, "AAA": 1, "ATA": 0, "TGT": 0, "CTC": 83, "CGT": 1, "GCT": 1, "GAT": 0, "TAC": 0, "GCG": 0, "GGA": 0, "TCG": 1, "GTA": 1, "CTG": 9, "GTT": 7, "AGG": 0, "AAC": 0, "ATG": 0, "CGG": 0, "CGA": 0, "TGG": 0, "ACG": 0, "TTA": 11, "CCT": 3, "CAC": 1, "TCC": 0, "TAT": 2, "ACT": 1, "TGA": 0, "ACA": 0, "CAG": 0, "TAG": 0, "ATT": 28, "AGA": 0, "CAT": 3, "TTT": 23, "TAA": 0, "GGG": 0, "GTG": 0, "AGT": 0}, "GAA": {"GGT": 1, "AAT": 7, "ATC": 0, "CCC": 0, "GCC": 2, "TTG": 0, "GAC": 18, "GCA": 15, "AGC": 0, "AAG": 2, "CCA": 2, "TGC": 0, "CCG": 0, "TCA": 2, "GTC": 0, "GGC": 0, "CTA": 0, "TCT": 0, "CAA": 11, "CGC": 0, "ACC": 1, "TTC": 1, "GAG": 357, "AAA": 74, "ATA": 0, "TGT": 0, "CTC": 0, "CGT": 0, "GCT": 4, "GAT": 52, "TAC": 0, "GCG": 2, "GGA": 32, "TCG": 0, "GTA": 15, "CTG": 0, "GTT": 1, "AGG": 0, "AAC": 3, "ATG": 0, "CGG": 0, "CGA": 0, "TGG": 0, "ACG": 0, "TTA": 0, "CCT": 0, "CAC": 0, "TCC": 0, "TAT": 3, "ACT": 0, "TGA": 0, "ACA": 6, "CAG": 1, "TAG": 0, "ATT": 2, "AGA": 2, "CAT": 0, "TTT": 1, "TAA": 3, "GGG": 2, "GTG": 1, "CTT": 0, "AGT": 0}, "GAC": {"GGT": 1, "AAT": 4, "ATC": 1, "CCC": 0, "GCC": 4, "TTG": 0, "GAA": 26, "GCA": 0, "AGC": 0, "AAG": 1, "CCA": 0, "TGC": 0, "CCG": 0, "TCA": 0, "GTC": 0, "GGC": 22, "CTA": 0, "TCT": 0, "CAA": 0, "CGC": 0, "ACC": 0, "TTC": 1, "GAG": 25, "AAA": 2, "ATA": 0, "TGT": 0, "CTC": 0, "CGT": 0, "GCT": 1, "GAT": 275, "TAC": 3, "GCG": 0, "GGA": 1, "TCG": 0, "GTA": 0, "CTG": 0, "GTT": 0, "AGG": 0, "AAC": 33, "ATG": 0, "CGG": 0, "CGA": 0, "TGG": 0, "ACG": 0, "TTA": 1, "CCT": 0, "CAC": 1, "TCC": 0, "TAT": 0, "ACT": 0, "TGA": 0, "ACA": 0, "CAG": 0, "TAG": 0, "ATT": 0, "AGA": 0, "CAT": 0, "TTT": 0, "TAA": 0, "GGG": 0, "GTG": 0, "CTT": 0, "AGT": 1}, "GAG": {"GGT": 4, "AAT": 2, "ATC": 0, "CCC": 0, "GCC": 1, "TTG": 0, "GAA": 405, "GAC": 9, "GCA": 5, "AGC": 0, "AAG": 32, "CCA": 1, "TGC": 0, "CCG": 0, "TCA": 1, "GTC": 0, "GGC": 2, "CTA": 0, "TCT": 0, "CAA": 1, "CGC": 0, "ACC": 0, "TTC": 0, "AAA": 8, "ATA": 0, "TGT": 0, "CTC": 0, "CGT": 0, "GCT": 2, "GAT": 69, "TAC": 0, "GCG": 8, "GGA": 4, "TCG": 1, "GTA": 1, "CTG": 0, "GTT": 1, "AGG": 0, "AAC": 1, "ATG": 0, "CGG": 0, "CGA": 0, "TGG": 1, "ACG": 1, "TTA": 0, "CCT": 1, "CAC": 1, "TCC": 0, "TAT": 3, "ACT": 0, "TGA": 0, "ACA": 1, "CAG": 8, "TAG": 1, "ATT": 0, "AGA": 1, "CAT": 0, "TTT": 0, "TAA": 0, "GGG": 16, "GTG": 11, "CTT": 0, "AGT": 0}, "GAT": {"GGT": 28, "AAT": 90, "ATC": 0, "CCC": 0, "GCC": 2, "TTG": 0, "GAA": 52, "GAC": 233, "GCA": 2, "AGC": 2, "AAG": 1, "CCA": 1, "TGC": 0, "CCG": 0, "TCA": 1, "GTC": 0, "GGC": 0, "CTA": 0, "TCT": 4, "CAA": 0, "CGC": 0, "ACC": 0, "TTC": 0, "GAG": 54, "AAA": 1, "ATA": 0, "TGT": 0, "CTC": 0, "CGT": 0, "GCT": 10, "TAC": 0, "GCG": 1, "GGA": 1, "TCG": 0, "GTA": 1, "CTG": 0, "GTT": 5, "AGG": 0, "AAC": 8, "ATG": 1, "CGG": 0, "CGA": 0, "TGG": 0, "ACG": 0, "TTA": 0, "CCT": 0, "CAC": 0, "TCC": 0, "TAT": 12, "ACT": 4, "TGA": 0, "ACA": 0, "CAG": 0, "TAG": 0, "ATT": 1, "AGA": 0, "CAT": 2, "TTT": 0, "TAA": 0, "GGG": 2, "GTG": 0, "CTT": 0, "AGT": 6}, "GCA": {"GGT": 0, "AAT": 3, "ATC": 0, "CCC": 0, "GCC": 92, "TTG": 1, "GAA": 21, "GAC": 1, "AGC": 0, "AAG": 0, "CCA": 2, "TGC": 0, "CCG": 1, "TCA": 32, "GTC": 0, "GGC": 1, "CTA": 2, "TCT": 5, "CAA": 1, "CGC": 0, "ACC": 1, "TTC": 0, "GAG": 2, "AAA": 2, "ATA": 2, "TGT": 0, "CTC": 0, "CGT": 0, "GCT": 214, "GAT": 2, "TAC": 1, "GCG": 137, "GGA": 5, "TCG": 2, "GTA": 63, "CTG": 0, "GTT": 2, "AGG": 0, "AAC": 0, "ATG": 1, "CGG": 0, "CGA": 0, "TGG": 0, "ACG": 2, "TTA": 2, "CCT": 2, "CAC": 0, "TCC": 1, "TAT": 1, "ACT": 7, "TGA": 0, "ACA": 78, "CAG": 0, "TAG": 0, "ATT": 1, "AGA": 0, "CAT": 0, "TTT": 0, "TAA": 0, "GGG": 1, "GTG": 3, "CTT": 0, "AGT": 2}, "GCC": {"GGT": 0, "AAT": 2, "ATC": 0, "CCC": 2, "TTG": 0, "GAA": 0, "GAC": 1, "GCA": 114, "AGC": 1, "AAG": 0, "CCA": 0, "TGC": 1, "CCG": 0, "TCA": 0, "GTC": 9, "GGC": 3, "CTA": 0, "TCT": 1, "CAA": 0, "CGC": 0, "ACC": 33, "TTC": 0, "GAG": 2, "AAA": 1, "ATA": 0, "TGT": 0, "CTC": 0, "CGT": 0, "GCT": 169, "GAT": 1, "TAC": 0, "GCG": 10, "GGA": 2, "TCG": 0, "GTA": 1, "CTG": 0, "GTT": 2, "AGG": 0, "AAC": 1, "ATG": 0, "CGG": 0, "CGA": 0, "TGG": 0, "ACG": 0, "TTA": 0, "CCT": 1, "CAC": 0, "TCC": 5, "TAT": 1, "ACT": 2, "TGA": 0, "ACA": 3, "CAG": 0, "TAG": 0, "ATT": 0, "AGA": 0, "CAT": 0, "TTT": 0, "TAA": 0, "GGG": 0, "GTG": 0, "CTT": 0, "AGT": 0}, "GCG": {"GGT": 0, "AAT": 0, "ATC": 0, "CCC": 0, "GCC": 13, "TTG": 0, "GAA": 0, "GAC": 1, "GCA": 112, "AGC": 0, "AAG": 0, "CCA": 0, "TGC": 0, "CCG": 0, "TCA": 1, "GTC": 0, "GGC": 0, "CTA": 0, "TCT": 0, "CAA": 0, "CGC": 0, "ACC": 0, "TTC": 0, "GAG": 2, "AAA": 0, "ATA": 0, "TGT": 0, "CTC": 0, "CGT": 0, "GCT": 52, "GAT": 1, "TAC": 0, "GGA": 1, "TCG": 3, "GTA": 1, "CTG": 0, "GTT": 0, "AGG": 0, "AAC": 0, "ATG": 1, "CGG": 0, "CGA": 0, "TGG": 0, "ACG": 8, "TTA": 0, "CCT": 0, "CAC": 0, "TCC": 0, "TAT": 0, "ACT": 0, "TGA": 0, "ACA": 2, "CAG": 0, "TAG": 0, "ATT": 0, "AGA": 0, "CAT": 0, "TTT": 0, "TAA": 0, "GGG": 2, "GTG": 10, "CTT": 0, "AGT": 0}, "GCT": {"GGT": 8, "AAT": 2, "ATC": 0, "CCC": 0, "GCC": 156, "TTG": 0, "GAA": 1, "GAC": 0, "GCA": 223, "AGC": 0, "AAG": 0, "CCA": 1, "TGC": 0, "CCG": 0, "TCA": 0, "GTC": 0, "GGC": 0, "CTA": 0, "TCT": 27, "CAA": 0, "CGC": 0, "ACC": 0, "TTC": 0, "GAG": 0, "AAA": 0, "ATA": 0, "TGT": 0, "CTC": 0, "CGT": 0, "GAT": 14, "TAC": 0, "GCG": 55, "GGA": 2, "TCG": 1, "GTA": 5, "CTG": 0, "GTT": 34, "AGG": 0, "AAC": 0, "ATG": 0, "CGG": 0, "CGA": 0, "TGG": 0, "ACG": 0, "TTA": 0, "CCT": 1, "CAC": 0, "TCC": 0, "TAT": 1, "ACT": 39, "TGA": 0, "ACA": 7, "CAG": 0, "TAG": 0, "ATT": 3, "AGA": 0, "CAT": 0, "TTT": 0, "TAA": 0, "GGG": 0, "GTG": 1, "CTT": 0, "AGT": 0}, "GGA": {"GGT": 229, "AAT": 1, "ATC": 0, "CCC": 0, "GCC": 0, "TTG": 0, "GAA": 46, "GAC": 1, "GCA": 8, "AGC": 2, "AAG": 0, "CCA": 0, "TGC": 0, "CCG": 0, "TCA": 0, "GTC": 0, "GGC": 106, "CTA": 1, "TCT": 0, "CAA": 1, "CGC": 0, "ACC": 1, "TTC": 0, "GAG": 1, "AAA": 5, "ATA": 0, "TGT": 0, "CTC": 0, "CGT": 0, "GCT": 1, "GAT": 4, "TAC": 1, "GCG": 0, "TCG": 0, "GTA": 8, "CTG": 0, "GTT": 0, "AGG": 1, "AAC": 1, "ATG": 0, "CGG": 0, "CGA": 1, "TGG": 0, "ACG": 0, "TTA": 0, "CCT": 1, "CAC": 0, "TCC": 0, "TAT": 0, "ACT": 0, "TGA": 0, "ACA": 0, "CAG": 0, "TAG": 0, "ATT": 0, "AGA": 11, "CAT": 0, "TTT": 0, "TAA": 1, "GGG": 234, "GTG": 0, "CTT": 0, "AGT": 3}, "GGC": {"GGT": 238, "AAT": 1, "ATC": 0, "CCC": 0, "GCC": 2, "TTG": 0, "GAA": 0, "GAC": 21, "GCA": 2, "AGC": 15, "AAG": 1, "CCA": 0, "TGC": 3, "CCG": 0, "TCA": 0, "GTC": 1, "CTA": 0, "TCT": 0, "CAA": 0, "CGC": 0, "ACC": 1, "TTC": 2, "GAG": 0, "AAA": 1, "ATA": 0, "TGT": 0, "CTC": 1, "CGT": 0, "GCT": 1, "GAT": 3, "TAC": 4, "GCG": 0, "GGA": 129, "TCG": 0, "GTA": 0, "CTG": 0, "GTT": 0, "AGG": 0, "AAC": 2, "ATG": 0, "CGG": 0, "CGA": 0, "TGG": 0, "ACG": 0, "TTA": 0, "CCT": 0, "CAC": 0, "TCC": 1, "TAT": 0, "ACT": 0, "TGA": 0, "ACA": 0, "CAG": 0, "TAG": 0, "ATT": 0, "AGA": 0, "CAT": 0, "TTT": 0, "TAA": 0, "GGG": 17, "GTG": 0, "CTT": 0, "AGT": 2}, "GGG": {"GGT": 59, "AAT": 0, "ATC": 0, "CCC": 0, "GCC": 0, "TTG": 1, "GAA": 4, "GAC": 0, "GCA": 0, "AGC": 0, "AAG": 0, "CCA": 0, "TGC": 0, "CCG": 0, "TCA": 0, "GTC": 0, "GGC": 12, "CTA": 0, "TCT": 0, "CAA": 0, "CGC": 0, "ACC": 0, "TTC": 0, "GAG": 12, "AAA": 0, "ATA": 0, "TGT": 0, "CTC": 0, "CGT": 0, "GCT": 0, "GAT": 0, "TAC": 1, "GCG": 0, "GGA": 220, "TCG": 0, "GTA": 0, "CTG": 0, "GTT": 0, "AGG": 3, "AAC": 0, "ATG": 0, "CGG": 1, "CGA": 0, "TGG": 0, "ACG": 0, "TTA": 0, "CCT": 0, "CAC": 0, "TCC": 0, "TAT": 0, "ACT": 0, "TGA": 0, "ACA": 1, "CAG": 1, "TAG": 0, "ATT": 0, "AGA": 0, "CAT": 0, "TTT": 0, "TAA": 0, "GTG": 3, "CTT": 0, "AGT": 0}, "GGT": {"AAT": 3, "ATC": 0, "CCC": 0, "GCC": 0, "TTG": 0, "GAA": 3, "GAC": 1, "GCA": 4, "AGC": 4, "AAG": 0, "CCA": 0, "TGC": 1, "CCG": 1, "TCA": 0, "GTC": 0, "GGC": 260, "CTA": 0, "TCT": 2, "CAA": 0, "CGC": 1, "ACC": 0, "TTC": 0, "GAG": 3, "AAA": 2, "ATA": 0, "TGT": 6, "CTC": 0, "CGT": 1, "GCT": 10, "GAT": 31, "TAC": 0, "GCG": 0, "GGA": 256, "TCG": 0, "GTA": 0, "CTG": 0, "GTT": 2, "AGG": 1, "AAC": 1, "ATG": 0, "CGG": 0, "CGA": 0, "TGG": 0, "ACG": 0, "TTA": 0, "CCT": 1, "CAC": 0, "TCC": 0, "TAT": 4, "ACT": 0, "TGA": 0, "ACA": 1, "CAG": 1, "TAG": 0, "ATT": 0, "AGA": 0, "CAT": 1, "TTT": 0, "TAA": 0, "GGG": 66, "GTG": 0, "CTT": 0, "AGT": 24}, "GTA": {"GGT": 0, "AAT": 2, "ATC": 5, "CCC": 0, "GCC": 2, "TTG": 0, "GAA": 13, "GAC": 0, "GCA": 40, "AGC": 0, "AAG": 0, "CCA": 2, "TGC": 0, "CCG": 0, "TCA": 1, "GTC": 58, "GGC": 0, "CTA": 8, "TCT": 0, "CAA": 1, "CGC": 0, "ACC": 1, "TTC": 0, "GAG": 5, "AAA": 3, "ATA": 93, "TGT": 0, "CTC": 0, "CGT": 0, "GCT": 2, "GAT": 0, "TAC": 0, "GCG": 1, "GGA": 7, "TCG": 0, "CTG": 0, "GTT": 126, "AGG": 0, "AAC": 0, "ATG": 2, "CGG": 0, "CGA": 0, "TGG": 0, "ACG": 1, "TTA": 6, "CCT": 0, "CAC": 0, "TCC": 0, "TAT": 0, "ACT": 0, "TGA": 0, "ACA": 8, "CAG": 0, "TAG": 0, "ATT": 7, "AGA": 0, "CAT": 0, "TTT": 0, "TAA": 0, "GGG": 0, "GTG": 122, "CTT": 1, "AGT": 1}, "GTC": {"GGT": 0, "AAT": 0, "ATC": 13, "CCC": 0, "GCC": 7, "TTG": 1, "GAA": 0, "GAC": 2, "GCA": 0, "AGC": 0, "AAG": 0, "CCA": 0, "TGC": 0, "CCG": 0, "TCA": 0, "GGC": 1, "CTA": 0, "TCT": 0, "CAA": 0, "CGC": 0, "ACC": 2, "TTC": 0, "GAG": 2, "AAA": 0, "ATA": 3, "TGT": 0, "CTC": 5, "CGT": 0, "GCT": 0, "GAT": 0, "TAC": 0, "GCG": 1, "GGA": 0, "TCG": 0, "GTA": 34, "CTG": 0, "GTT": 105, "AGG": 0, "AAC": 0, "ATG": 0, "CGG": 0, "CGA": 0, "TGG": 0, "ACG": 0, "TTA": 0, "CCT": 0, "CAC": 0, "TCC": 0, "TAT": 0, "ACT": 0, "TGA": 0, "ACA": 0, "CAG": 0, "TAG": 0, "ATT": 1, "AGA": 0, "CAT": 0, "TTT": 0, "TAA": 0, "GGG": 0, "GTG": 7, "CTT": 0, "AGT": 0}, "GTG": {"GGT": 0, "AAT": 0, "ATC": 1, "CCC": 0, "GCC": 0, "TTG": 3, "GAA": 2, "GAC": 0, "GCA": 0, "AGC": 0, "AAG": 1, "CCA": 0, "TGC": 0, "CCG": 0, "TCA": 0, "GTC": 11, "GGC": 0, "CTA": 2, "TCT": 0, "CAA": 0, "CGC": 0, "ACC": 0, "TTC": 0, "GAG": 12, "AAA": 0, "ATA": 2, "TGT": 0, "CTC": 1, "CGT": 0, "GCT": 0, "GAT": 1, "TAC": 0, "GCG": 9, "GGA": 0, "TCG": 0, "GTA": 114, "CTG": 2, "GTT": 34, "AGG": 0, "AAC": 0, "ATG": 12, "CGG": 0, "CGA": 0, "TGG": 0, "ACG": 0, "TTA": 0, "CCT": 0, "CAC": 1, "TCC": 0, "TAT": 0, "ACT": 0, "TGA": 0, "ACA": 0, "CAG": 0, "TAG": 0, "ATT": 0, "AGA": 0, "CAT": 0, "TTT": 0, "TAA": 0, "GGG": 1, "CTT": 1, "AGT": 1}, "GTT": {"GGT": 1, "AAT": 2, "ATC": 2, "CCC": 0, "GCC": 2, "TTG": 9, "GAA": 3, "GAC": 0, "GCA": 6, "AGC": 0, "AAG": 1, "CCA": 0, "TGC": 0, "CCG": 0, "TCA": 0, "GTC": 86, "GGC": 0, "CTA": 1, "TCT": 0, "CAA": 1, "CGC": 0, "ACC": 0, "TTC": 0, "GAG": 3, "AAA": 0, "ATA": 7, "TGT": 0, "CTC": 0, "CGT": 1, "GCT": 33, "GAT": 5, "TAC": 0, "GCG": 0, "GGA": 0, "TCG": 0, "GTA": 133, "CTG": 0, "AGG": 0, "AAC": 1, "ATG": 2, "CGG": 0, "CGA": 0, "TGG": 0, "ACG": 2, "TTA": 8, "CCT": 1, "CAC": 0, "TCC": 0, "TAT": 0, "ACT": 3, "TGA": 0, "ACA": 0, "CAG": 0, "TAG": 0, "ATT": 111, "AGA": 0, "CAT": 0, "TTT": 7, "TAA": 0, "GGG": 1, "GTG": 25, "CTT": 10, "AGT": 0}, "TAA": {"GGT": 0, "AAT": 0, "ATC": 0, "CCC": 0, "GCC": 0, "TTG": 0, "GAA": 2, "GAC": 0, "GCA": 0, "AGC": 0, "AAG": 0, "CCA": 0, "TGC": 0, "CCG": 0, "TCA": 0, "GTC": 0, "GGC": 0, "CTA": 0, "TCT": 0, "CAA": 0, "CGC": 0, "ACC": 0, "TTC": 0, "GAG": 0, "AAA": 1, "ATA": 0, "TGT": 0, "CTC": 0, "CGT": 0, "GCT": 0, "GAT": 0, "TAC": 1, "GCG": 0, "GGA": 0, "TCG": 0, "GTA": 0, "CTG": 0, "GTT": 0, "AGG": 0, "AAC": 0, "ATG": 0, "CGG": 0, "CGA": 0, "TGG": 0, "ACG": 0, "TTA": 3, "CCT": 0, "CAC": 0, "TCC": 0, "TAT": 0, "ACT": 0, "TGA": 0, "ACA": 0, "CAG": 0, "TAG": 4, "ATT": 0, "AGA": 0, "CAT": 0, "TTT": 0, "GGG": 0, "GTG": 0, "CTT": 0, "AGT": 0}, "TAC": {"GGT": 0, "AAT": 2, "ATC": 0, "CCC": 0, "GCC": 0, "TTG": 1, "GAA": 1, "GAC": 2, "GCA": 0, "AGC": 1, "AAG": 0, "CCA": 0, "TGC": 5, "CCG": 0, "TCA": 0, "GTC": 0, "GGC": 4, "CTA": 0, "TCT": 0, "CAA": 0, "CGC": 2, "ACC": 0, "TTC": 13, "GAG": 0, "AAA": 0, "ATA": 0, "TGT": 1, "CTC": 0, "CGT": 0, "GCT": 0, "GAT": 1, "GCG": 0, "GGA": 0, "TCG": 0, "GTA": 0, "CTG": 0, "GTT": 0, "AGG": 0, "AAC": 5, "ATG": 0, "CGG": 0, "CGA": 0, "TGG": 1, "ACG": 0, "TTA": 1, "CCT": 0, "CAC": 8, "TCC": 1, "TAT": 192, "ACT": 0, "TGA": 1, "ACA": 0, "CAG": 0, "TAG": 0, "ATT": 0, "AGA": 0, "CAT": 1, "TTT": 1, "TAA": 0, "GGG": 0, "GTG": 0, "CTT": 0, "AGT": 1}, "TAG": {"GGT": 0, "AAT": 0, "ATC": 0, "CCC": 0, "GCC": 0, "TTG": 0, "GAA": 0, "GAC": 0, "GCA": 0, "AGC": 0, "AAG": 0, "CCA": 0, "TGC": 0, "CCG": 0, "TCA": 0, "GTC": 0, "GGC": 0, "CTA": 0, "TCT": 0, "CAA": 0, "CGC": 0, "ACC": 0, "TTC": 0, "GAG": 0, "AAA": 0, "ATA": 0, "TGT": 0, "CTC": 0, "CGT": 0, "GCT": 0, "GAT": 0, "TAC": 0, "GCG": 0, "GGA": 0, "TCG": 0, "GTA": 0, "CTG": 0, "GTT": 0, "AGG": 0, "AAC": 0, "ATG": 0, "CGG": 0, "CGA": 0, "TGG": 0, "ACG": 0, "TTA": 0, "CCT": 0, "CAC": 0, "TCC": 0, "TAT": 0, "ACT": 0, "TGA": 0, "ACA": 0, "CAG": 0, "ATT": 0, "AGA": 0, "CAT": 0, "TTT": 0, "TAA": 6, "GGG": 0, "GTG": 0, "CTT": 0, "AGT": 1}, "TAT": {"GGT": 2, "AAT": 12, "ATC": 0, "CCC": 0, "GCC": 0, "TTG": 1, "GAA": 9, "GAC": 1, "GCA": 0, "AGC": 0, "AAG": 0, "CCA": 0, "TGC": 0, "CCG": 0, "TCA": 1, "GTC": 0, "GGC": 0, "CTA": 0, "TCT": 10, "CAA": 2, "CGC": 0, "ACC": 1, "TTC": 2, "GAG": 1, "AAA": 2, "ATA": 0, "TGT": 11, "CTC": 0, "CGT": 4, "GCT": 0, "GAT": 16, "TAC": 201, "GCG": 0, "GGA": 1, "TCG": 4, "GTA": 0, "CTG": 0, "GTT": 0, "AGG": 0, "AAC": 0, "ATG": 1, "CGG": 0, "CGA": 0, "TGG": 5, "ACG": 0, "TTA": 1, "CCT": 0, "CAC": 1, "TCC": 1, "ACT": 0, "TGA": 1, "ACA": 1, "CAG": 0, "TAG": 1, "ATT": 2, "AGA": 1, "CAT": 19, "TTT": 23, "TAA": 2, "GGG": 0, "GTG": 0, "CTT": 1, "AGT": 1}, "TCA": {"GGT": 0, "AAT": 1, "ATC": 0, "CCC": 0, "GCC": 1, "TTG": 2, "GAA": 3, "GAC": 0, "GCA": 25, "AGC": 0, "AAG": 1, "CCA": 11, "TGC": 0, "CCG": 3, "GTC": 0, "GGC": 0, "CTA": 0, "TCT": 113, "CAA": 5, "CGC": 0, "ACC": 1, "TTC": 0, "GAG": 2, "AAA": 2, "ATA": 1, "TGT": 0, "CTC": 0, "CGT": 0, "GCT": 1, "GAT": 1, "TAC": 0, "GCG": 3, "GGA": 1, "TCG": 135, "GTA": 0, "CTG": 0, "GTT": 1, "AGG": 0, "AAC": 0, "ATG": 0, "CGG": 0, "CGA": 0, "TGG": 0, "ACG": 3, "TTA": 18, "CCT": 0, "CAC": 0, "TCC": 13, "TAT": 0, "ACT": 6, "TGA": 0, "ACA": 46, "CAG": 0, "TAG": 0, "ATT": 0, "AGA": 0, "CAT": 0, "TTT": 0, "TAA": 1, "GGG": 0, "GTG": 0, "CTT": 0, "AGT": 1}, "TCC": {"GGT": 0, "AAT": 0, "ATC": 0, "CCC": 8, "GCC": 9, "TTG": 0, "GAA": 0, "GAC": 0, "GCA": 0, "AGC": 1, "AAG": 0, "CCA": 0, "TGC": 0, "CCG": 0, "TCA": 17, "GTC": 1, "GGC": 0, "CTA": 0, "TCT": 32, "CAA": 0, "CGC": 0, "ACC": 3, "TTC": 4, "GAG": 0, "AAA": 0, "ATA": 0, "TGT": 0, "CTC": 0, "CGT": 0, "GCT": 2, "GAT": 0, "TAC": 2, "GCG": 0, "GGA": 0, "TCG": 0, "GTA": 0, "CTG": 0, "GTT": 0, "AGG": 0, "AAC": 1, "ATG": 0, "CGG": 0, "CGA": 0, "TGG": 0, "ACG": 0, "TTA": 0, "CCT": 0, "CAC": 1, "TAT": 0, "ACT": 2, "TGA": 0, "ACA": 1, "CAG": 0, "TAG": 0, "ATT": 0, "AGA": 0, "CAT": 0, "TTT": 0, "TAA": 0, "GGG": 0, "GTG": 0, "CTT": 0, "AGT": 0}, "TCG": {"GGT": 0, "AAT": 0, "ATC": 0, "CCC": 1, "GCC": 0, "TTG": 14, "GAA": 1, "GAC": 0, "GCA": 3, "AGC": 0, "AAG": 0, "CCA": 0, "TGC": 0, "CCG": 5, "TCA": 126, "GTC": 0, "GGC": 0, "CTA": 0, "TCT": 54, "CAA": 0, "CGC": 0, "ACC": 0, "TTC": 0, "GAG": 0, "AAA": 1, "ATA": 2, "TGT": 0, "CTC": 0, "CGT": 0, "GCT": 1, "GAT": 0, "TAC": 0, "GCG": 6, "GGA": 1, "GTA": 0, "CTG": 0, "GTT": 0, "AGG": 0, "AAC": 0, "ATG": 0, "CGG": 0, "CGA": 0, "TGG": 1, "ACG": 4, "TTA": 1, "CCT": 0, "CAC": 0, "TCC": 1, "TAT": 1, "ACT": 2, "TGA": 0, "ACA": 0, "CAG": 0, "TAG": 1, "ATT": 0, "AGA": 0, "CAT": 0, "TTT": 0, "TAA": 0, "GGG": 0, "GTG": 0, "CTT": 0, "AGT": 1}, "TCT": {"GGT": 1, "AAT": 2, "ATC": 0, "CCC": 1, "GCC": 0, "TTG": 0, "GAA": 2, "GAC": 0, "GCA": 4, "AGC": 0, "AAG": 0, "CCA": 1, "TGC": 0, "CCG": 0, "TCA": 97, "GTC": 0, "GGC": 0, "CTA": 0, "CAA": 0, "CGC": 0, "ACC": 0, "TTC": 2, "GAG": 0, "AAA": 0, "ATA": 0, "TGT": 1, "CTC": 0, "CGT": 0, "GCT": 16, "GAT": 2, "TAC": 0, "GCG": 0, "GGA": 0, "TCG": 40, "GTA": 0, "CTG": 0, "GTT": 1, "AGG": 0, "AAC": 0, "ATG": 0, "CGG": 0, "CGA": 0, "TGG": 0, "ACG": 0, "TTA": 0, "CCT": 21, "CAC": 0, "TCC": 38, "TAT": 17, "ACT": 21, "TGA": 0, "ACA": 6, "CAG": 0, "TAG": 0, "ATT": 0, "AGA": 0, "CAT": 0, "TTT": 4, "TAA": 0, "GGG": 0, "GTG": 1, "CTT": 0, "AGT": 1}, "TGA": {"GGT": 0, "AAT": 0, "ATC": 0, "CCC": 0, "GCC": 0, "TTG": 0, "GAA": 0, "GAC": 0, "GCA": 0, "AGC": 0, "AAG": 0, "CCA": 0, "TGC": 0, "CCG": 0, "TCA": 0, "GTC": 0, "GGC": 0, "CTA": 0, "TCT": 0, "CAA": 0, "CGC": 0, "ACC": 0, "TTC": 0, "GAG": 0, "AAA": 0, "ATA": 0, "TGT": 0, "CTC": 0, "CGT": 0, "GCT": 0, "GAT": 0, "TAC": 0, "GCG": 0, "GGA": 0, "TCG": 0, "GTA": 0, "CTG": 0, "GTT": 0, "AGG": 0, "AAC": 0, "ATG": 0, "CGG": 0, "CGA": 0, "TGG": 0, "ACG": 0, "TTA": 0, "CCT": 0, "CAC": 0, "TCC": 0, "TAT": 0, "ACT": 0, "ACA": 0, "CAG": 0, "TAG": 0, "ATT": 0, "AGA": 1, "CAT": 0, "TTT": 0, "TAA": 1, "GGG": 0, "GTG": 0, "CTT": 0, "AGT": 0}, "TGC": {"GGT": 0, "AAT": 0, "ATC": 0, "CCC": 0, "GCC": 0, "TTG": 0, "GAA": 0, "GAC": 1, "GCA": 0, "AGC": 4, "AAG": 0, "CCA": 0, "CCG": 0, "TCA": 1, "GTC": 0, "GGC": 0, "CTA": 0, "TCT": 0, "CAA": 0, "CGC": 1, "ACC": 0, "TTC": 1, "GAG": 0, "AAA": 0, "ATA": 0, "TGT": 68, "CTC": 0, "CGT": 0, "GCT": 0, "GAT": 0, "TAC": 9, "GCG": 0, "GGA": 0, "TCG": 0, "GTA": 0, "CTG": 0, "GTT": 0, "AGG": 0, "AAC": 0, "ATG": 0, "CGG": 0, "CGA": 0, "TGG": 0, "ACG": 0, "TTA": 0, "CCT": 0, "CAC": 1, "TCC": 0, "TAT": 3, "ACT": 0, "TGA": 0, "ACA": 0, "CAG": 0, "TAG": 0, "ATT": 0, "AGA": 0, "CAT": 0, "TTT": 0, "TAA": 0, "GGG": 0, "GTG": 0, "CTT": 0, "AGT": 0}, "TGG": {"GGT": 0, "AAT": 0, "ATC": 0, "CCC": 0, "GCC": 0, "TTG": 5, "GAA": 0, "GAC": 0, "GCA": 0, "AGC": 0, "AAG": 0, "CCA": 0, "TGC": 0, "CCG": 0, "TCA": 1, "GTC": 0, "GGC": 0, "CTA": 0, "TCT": 0, "CAA": 0, "CGC": 0, "ACC": 1, "TTC": 0, "GAG": 0, "AAA": 1, "ATA": 0, "TGT": 1, "CTC": 0, "CGT": 0, "GCT": 0, "GAT": 0, "TAC": 1, "GCG": 0, "GGA": 1, "TCG": 0, "GTA": 0, "CTG": 0, "GTT": 0, "AGG": 1, "AAC": 0, "ATG": 1, "CGG": 0, "CGA": 0, "ACG": 0, "TTA": 0, "CCT": 0, "CAC": 0, "TCC": 0, "TAT": 2, "ACT": 0, "TGA": 1, "ACA": 0, "CAG": 0, "TAG": 0, "ATT": 0, "AGA": 1, "CAT": 0, "TTT": 4, "TAA": 0, "GGG": 1, "GTG": 0, "CTT": 0, "AGT": 1}, "TGT": {"GGT": 7, "AAT": 0, "ATC": 0, "CCC": 0, "GCC": 0, "TTG": 0, "GAA": 1, "GAC": 0, "GCA": 0, "AGC": 0, "AAG": 0, "CCA": 0, "TGC": 95, "CCG": 0, "TCA": 1, "GTC": 0, "GGC": 0, "CTA": 0, "TCT": 1, "CAA": 0, "CGC": 0, "ACC": 0, "TTC": 1, "GAG": 0, "AAA": 0, "ATA": 0, "CTC": 0, "CGT": 3, "GCT": 0, "GAT": 0, "TAC": 1, "GCG": 0, "GGA": 1, "TCG": 0, "GTA": 0, "CTG": 0, "GTT": 0, "AGG": 0, "AAC": 0, "ATG": 0, "CGG": 0, "CGA": 0, "TGG": 2, "ACG": 0, "TTA": 0, "CCT": 1, "CAC": 0, "TCC": 0, "TAT": 11, "ACT": 0, "TGA": 0, "ACA": 0, "CAG": 0, "TAG": 0, "ATT": 0, "AGA": 0, "CAT": 1, "TTT": 2, "TAA": 0, "GGG": 0, "GTG": 0, "CTT": 0, "AGT": 6}, "TTA": {"GGT": 0, "AAT": 0, "ATC": 0, "CCC": 0, "GCC": 0, "TTG": 195, "GAA": 0, "GAC": 0, "GCA": 2, "AGC": 0, "AAG": 0, "CCA": 0, "TGC": 0, "CCG": 0, "TCA": 11, "GTC": 0, "GGC": 0, "CTA": 96, "TCT": 2, "CAA": 1, "CGC": 0, "ACC": 0, "TTC": 6, "GAG": 0, "AAA": 0, "ATA": 38, "TGT": 0, "CTC": 2, "CGT": 0, "GCT": 0, "GAT": 0, "TAC": 0, "GCG": 0, "GGA": 1, "TCG": 0, "GTA": 6, "CTG": 2, "GTT": 1, "AGG": 0, "AAC": 0, "ATG": 3, "CGG": 0, "CGA": 1, "TGG": 0, "ACG": 0, "CCT": 0, "CAC": 0, "TCC": 0, "TAT": 4, "ACT": 0, "TGA": 0, "ACA": 2, "CAG": 0, "TAG": 0, "ATT": 1, "AGA": 0, "CAT": 0, "TTT": 10, "TAA": 5, "GGG": 0, "GTG": 0, "CTT": 14, "AGT": 0}, "TTC": {"GGT": 0, "AAT": 0, "ATC": 1, "CCC": 0, "GCC": 0, "TTG": 3, "GAA": 0, "GAC": 0, "GCA": 0, "AGC": 0, "AAG": 0, "CCA": 0, "TGC": 0, "CCG": 0, "TCA": 0, "GTC": 3, "GGC": 0, "CTA": 0, "TCT": 0, "CAA": 0, "CGC": 0, "ACC": 0, "GAG": 0, "AAA": 0, "ATA": 0, "TGT": 0, "CTC": 6, "CGT": 0, "GCT": 0, "GAT": 0, "TAC": 12, "GCG": 1, "GGA": 0, "TCG": 0, "GTA": 0, "CTG": 0, "GTT": 0, "AGG": 0, "AAC": 0, "ATG": 0, "CGG": 0, "CGA": 0, "TGG": 0, "ACG": 0, "TTA": 13, "CCT": 0, "CAC": 0, "TCC": 6, "TAT": 0, "ACT": 0, "TGA": 0, "ACA": 0, "CAG": 0, "TAG": 0, "ATT": 1, "AGA": 0, "CAT": 1, "TTT": 187, "TAA": 0, "GGG": 0, "GTG": 0, "CTT": 2, "AGT": 0}, "TTG": {"GGT": 0, "AAT": 0, "ATC": 0, "CCC": 0, "GCC": 0, "GAA": 0, "GAC": 0, "GCA": 0, "AGC": 0, "AAG": 1, "CCA": 0, "TGC": 0, "CCG": 0, "TCA": 0, "GTC": 1, "GGC": 0, "CTA": 9, "TCT": 0, "CAA": 0, "CGC": 0, "ACC": 0, "TTC": 0, "GAG": 0, "AAA": 0, "ATA": 2, "TGT": 0, "CTC": 2, "CGT": 0, "GCT": 0, "GAT": 0, "TAC": 0, "GCG": 1, "GGA": 0, "TCG": 5, "GTA": 1, "CTG": 47, "GTT": 2, "AGG": 0, "AAC": 0, "ATG": 19, "CGG": 0, "CGA": 0, "TGG": 3, "ACG": 0, "TTA": 263, "CCT": 0, "CAC": 0, "TCC": 0, "TAT": 0, "ACT": 0, "TGA": 1, "ACA": 0, "CAG": 0, "TAG": 1, "ATT": 0, "AGA": 0, "CAT": 0, "TTT": 14, "TAA": 0, "GGG": 0, "GTG": 6, "CTT": 8, "AGT": 0}, "TTT": {"GGT": 0, "AAT": 0, "ATC": 0, "CCC": 0, "GCC": 0, "TTG": 13, "GAA": 0, "GAC": 0, "GCA": 0, "AGC": 0, "AAG": 0, "CCA": 0, "TGC": 0, "CCG": 0, "TCA": 1, "GTC": 0, "GGC": 0, "CTA": 1, "TCT": 12, "CAA": 0, "CGC": 0, "ACC": 0, "TTC": 156, "GAG": 0, "AAA": 0, "ATA": 1, "TGT": 2, "CTC": 2, "CGT": 0, "GCT": 0, "GAT": 1, "TAC": 1, "GCG": 0, "GGA": 1, "TCG": 0, "GTA": 1, "CTG": 0, "GTT": 9, "AGG": 0, "AAC": 0, "ATG": 0, "CGG": 0, "CGA": 0, "TGG": 0, "ACG": 0, "TTA": 14, "CCT": 0, "CAC": 0, "TCC": 1, "TAT": 24, "ACT": 0, "TGA": 0, "ACA": 0, "CAG": 0, "TAG": 0, "ATT": 13, "AGA": 0, "CAT": 0, "TAA": 0, "GGG": 0, "GTG": 0, "CTT": 29, "AGT": 0}}